{
  "domainId": "domainId_compatible",
  "type": "page_view_or_other",
  "clientId": 555,
  "clientGuild": "client_guid",
  "id_config": "hash_configu",
  "filter": {
    "in_segment": ["hash_segmentu"],
    "not_in_segment": ["hash_segmentu"],
    "in_tag": ["tag"],
    "not_in_tag": ["tag"],
    "priority": 10,
    "filtering_variable":"variable_name/column_name/etc"
  },
  "steps":
  [{
    "condition":"10<x<30",
    "recommendations": {
      "recommendation_type": "standard/custom"
    },
    "segmentation": {
      "segmentation_type": "business/graphics/both"
    },
    "channels": {
      "email": {
        "template": "template_id",
        "dynamic_fields": "how?",
        "send_time": "now/delayed"
      },
      "facebook": {
        "audience": "audience_id",
        "add_time": "now/delayed",
        "remove_before": "date"
      },
      "adwords": {
        "audience": "audience_id",
        "add_time": "now/delayed",
        "remove_before": "date"
      },
      "adserving": {
        "provider": "BlueKai",
        "segment": "segment_id",
        "add_time": "now/delayed",
        "remove_before": "date",
        "template": "template_id/none"
      },
      "action": [{
        "action_family": "tags/list",
        "action_type": "add/remove/check/update...",
        "action_time": "now/triggered",
        "action_trigger": "empty/condition",
        "action_subject": "tag_name/segment_hash"
      }]
    },
    "next_flow": {
      "clientId": "clientId_compatible",
      "type": "syntetic",
      "config": "hash_configu"
    }
  }]
}
